reactive_pydantic/__init__.py
reactive_pydantic/core.py
reactive_pydantic/events.py
reactive_pydantic/operators.py
reactive_pydantic-0.1.0.dist-info/METADATA
reactive_pydantic-0.1.0.dist-info/WHEEL
reactive_pydantic-0.1.0.dist-info/RECORD
