Metadata-Version: 2.3
Name: reactive-pydantic
Version: 0.1.0
Summary: A library for creating reactive Pydantic models using RxPy.
License: MIT
Keywords: pydantic,reactive,rxpy,observables
Author: Your Name
Author-email: dogukan.altay@yahoo.com
Requires-Python: >=3.8,<4.0
Classifier: License :: OSI Approved :: MIT License
Classifier: Programming Language :: Python :: 3
Classifier: Programming Language :: Python :: 3.8
Classifier: Programming Language :: Python :: 3.9
Classifier: Programming Language :: Python :: 3.10
Classifier: Programming Language :: Python :: 3.11
Classifier: Programming Language :: Python :: 3.12
Classifier: Programming Language :: Python :: 3.13
Requires-Dist: pydantic (>=2.0.0,<3.0.0)
Requires-Dist: reactivex (>=4.0.4,<5.0.0)
Project-URL: Homepage, https://github.com/dogukanaltay/reactive-pydantic
Project-URL: Repository, https://github.com/dogukanaltay/reactive-pydantic
